pywebtasks-0.1.3.dist-info/DESCRIPTION.rst
pywebtasks-0.1.3.dist-info/metadata.json
pywebtasks-0.1.3.dist-info/METADATA
pywebtasks-0.1.3.dist-info/top_level.txt
pywebtasks-0.1.3.dist-info/RECORD
pywebtasks-0.1.3.dist-info/WHEEL
pywebtasks-0.1.3.dist-info/pbr.json
pywebtasks/langs.py
pywebtasks/__init__.py
pywebtasks/webtasks.py
pywebtasks/tokens.py
pywebtasks/compat.py
