Metadata-Version: 2.0
Name: pywebtasks
Version: 0.1.3
Summary: Python wrapper for Auth0's Webtask API.
Home-page: https://github.com/ssebastianj/pywebtasks
Author: Sebastián J. Seba
Author-email: ssebastianj@gmail.com
License: MIT
Keywords: pywebtasks
Platform: UNKNOWN
Classifier: Development Status :: 2 - Pre-Alpha
Classifier: Intended Audience :: Developers
Classifier: License :: OSI Approved :: MIT License
Classifier: Natural Language :: English
Classifier: Programming Language :: Python
Classifier: Programming Language :: Python :: 2
Classifier: Programming Language :: Python :: 2.6
Classifier: Programming Language :: Python :: 2.7
Classifier: Programming Language :: Python :: 3
Classifier: Programming Language :: Python :: 3.3
Classifier: Programming Language :: Python :: 3.4
Requires-Dist: requests (~=2.7.0)
